.etltest-settings.yml
CHANGES.txt
CONTRIBUTING.md
LICENSE
MANIFEST.in
README.md
setup.py
docs/source/contributing.rst
docs/source/index.rst
docs/source/setup.rst
docs/source/intro/intro.rst
docs/source/intro/overview.rst
docs/source/settings/connections.rst
docs/source/settings/data_integration.rst
docs/source/settings/etltest.rst
docs/source/settings/properties.rst
docs/source/settings/settings.rst
docs/source/standards/sample_data.rst
docs/source/standards/standards.rst
docs/source/standards/test.rst
docs/source/standards/test_components.rst
docs/source/standards/templates/templates.rst
docs/source/standards/templates/test.rst
docs/source/standards/templates/test_suite.rst
docs/source/tutorial/configuring_data_integration_tool.rst
docs/source/tutorial/creating_sample_data_set.rst
docs/source/tutorial/etlunittest_build_script.rst
docs/source/tutorial/executing_tests.rst
docs/source/tutorial/generating_test_code.rst
docs/source/tutorial/preparing_environment.rst
docs/source/tutorial/tutorial.rst
docs/source/tutorial/writing_first_test.rst
docs/source/tutorial/yaml_details_stub.rst
etlTest.egg-info/PKG-INFO
etlTest.egg-info/SOURCES.txt
etlTest.egg-info/dependency_links.txt
etlTest.egg-info/entry_points.txt
etlTest.egg-info/requires.txt
etlTest.egg-info/top_level.txt
etltest/__init__.py
etltest/code_executor.py
etltest/code_generator.py
etltest/data_connector.py
etltest/etlTest.py
etltest/process_executor.py
etltest/samples/data/etlUnitTest/user_geo_ref.yml
etltest/samples/data/etlUnitTest/user_geo_ref_defined_column.yml
etltest/samples/data/etlUnitTest/users.yml
etltest/samples/etl/shared.xml
etltest/samples/etl/data_mart/user_dim_jb.kjb
etltest/samples/etl/data_mart/user_dim_load_tr.ktr
etltest/samples/output/DataMart/UsersDim.py
etltest/samples/output/DataMart/UsersDim.pyc
etltest/samples/output/DataMart/__pycache__/UsersDim.cpython-33.pyc
etltest/samples/output/main/help_arg.txt
etltest/samples/output/main/in_dir_generation.txt
etltest/samples/output/main/in_file_generation.txt
etltest/samples/output/main/no_args.txt
etltest/samples/test/dataMart/users_dim.yml
etltest/templates/output/fixture.jinja2
etltest/templates/output/suite.jinja2
