Metadata-Version: 1.1
Name: etlTest
Version: 0.1.5
Summary: Automated and tool agnostic data integration testing tool.
Home-page: https://github.com/OpenDataAlex/etlTest
Author: Alex Meadows, Coty Sutherland
Author-email: alexmeadows@bluefiredatasolutions.com
License: GNU GENERAL PUBLIC LICENSE Version 3
Keywords: etl data_integration testing automation
Platform: UNKNOWN
Classifier: Programming Language :: Python
Classifier: Development Status :: 4 - Beta
Classifier: Natural Language :: English
Classifier: Environment :: Console
Classifier: Intended Audience :: Developers
